QcrBot_SDK/__init__.py
QcrBot_SDK/adapters/__init__.py
QcrBot_SDK/adapters/websocket.py
QcrBot_SDK/api/action.py
QcrBot_SDK/api/client.py
QcrBot_SDK/api/types.py
QcrBot_SDK/core/bot.py
QcrBot_SDK/core/dispatcher.py
QcrBot_SDK/event/__init__.py
QcrBot_SDK/event/base.py
QcrBot_SDK/event/models.py
QcrBot_SDK/event/parser.py
QcrBot_SDK/event/typing.py
QcrBot_SDK/message/__init__.py
QcrBot_SDK/message/message.py
QcrBot_SDK/message/segment.py
QcrBot_SDK/utils/__init__.py
QcrBot_SDK/utils/cq_code.py
QcrBot_SDK/utils/exception.py
QcrBot_SDK/utils/helpers.py
QcrBot_SDK/utils/log.py
qcrbot_sdk-1.0.0.dist-info/licenses/LICENSE
qcrbot_sdk-1.0.0.dist-info/METADATA
qcrbot_sdk-1.0.0.dist-info/WHEEL
qcrbot_sdk-1.0.0.dist-info/top_level.txt
qcrbot_sdk-1.0.0.dist-info/RECORD
