Metadata-Version: 2.4
Name: QcrBot_SDK
Version: 1.0.0
Summary: 一个简洁易用的 OneBot v11 Python SDK
License:                     GNU AFFERO GENERAL PUBLIC LICENSE
Project-URL: Homepage, https://github.com/QcrTiMo/QcrBot_SDK
Project-URL: Repository, https://github.com/QcrTiMo/QcrBot_SDK
Project-URL: Documentation, https://qcrtimo.com/?docs=%e5%bc%80%e5%a7%8b%e6%9e%84%e5%bb%ba%e4%bd%a0%e7%9a%84onebot%e5%ba%94%e7%94%a8-%e5%ae%9e%e4%be%8b%e5%8c%96bot%e5%af%b9%e8%b1%a1
Classifier: Development Status :: 3 - Alpha
Classifier: Intended Audience :: Developers
Classifier: License :: OSI Approved :: GNU Affero General Public License v3
Classifier: Operating System :: OS Independent
Classifier: Programming Language :: Python
Classifier: Programming Language :: Python :: 3
Classifier: Programming Language :: Python :: 3.8
Classifier: Programming Language :: Python :: 3.9
Classifier: Programming Language :: Python :: 3.10
Classifier: Programming Language :: Python :: 3.11
Classifier: Programming Language :: Python :: 3.12
Classifier: Topic :: Communications :: Chat
Classifier: Topic :: Software Development :: Libraries :: Python Modules
Classifier: Framework :: AsyncIO
Requires-Python: >=3.8
License-File: LICENSE
Requires-Dist: websockets>=12.0
Requires-Dist: pydantic>=2.0
Dynamic: license-file
